journal_to_fedora_messaging_messages/__init__.py
journal_to_fedora_messaging_messages/base.py
journal_to_fedora_messaging_messages/ipa.py
journal_to_fedora_messaging_messages-1.0.3.dist-info/LICENSES/LGPL-3.0-or-later.txt
journal_to_fedora_messaging_messages-1.0.3.dist-info/METADATA
journal_to_fedora_messaging_messages-1.0.3.dist-info/WHEEL
journal_to_fedora_messaging_messages-1.0.3.dist-info/entry_points.txt
journal_to_fedora_messaging_messages-1.0.3.dist-info/RECORD
